rfcparser/__init__.py
rfcparser/core.py
rfcparser/exceptions.py
rfcparser/object_abstractions.py
rfcparser/grammars/rfc1034_domain.lark
rfcparser/grammars/rfc3986_uri.lark
rfcparser/grammars/rfc5234_core.lark
rfcparser/grammars/rfc6265_date.lark
rfcparser/grammars/rfc6265_set_cookie.lark
rfcparser/grammars/rfc822_domain.lark
rfcparser-0.0.8.dist-info/METADATA
rfcparser-0.0.8.dist-info/WHEEL
rfcparser-0.0.8.dist-info/licenses/LICENSE
rfcparser-0.0.8.dist-info/RECORD
