Metadata-Version: 2.1
Name: rfcparser
Version: 0.0.8
Summary: Rfcparser is a Python tool that makes it easy to parse common RFC syntaxes. Rfcparser takes a raw string as input, parses, validates, and returns Python objects to simplify the processing of RFC syntaxes.
Project-URL: Homepage, https://github.com/karosis88/rfcparser.git
Project-URL: Source, https://github.com/karosis88/rfcparser.git
License-File: LICENSE
Classifier: Intended Audience :: Developers
Classifier: Programming Language :: Python :: Implementation :: CPython
Classifier: Topic :: Internet :: WWW/HTTP
Requires-Dist: lark
